romance/__init__.py
romance/core.py
romance-1.0.dist-info/METADATA
romance-1.0.dist-info/WHEEL
romance-1.0.dist-info/top_level.txt
romance-1.0.dist-info/RECORD
