Metadata-Version: 2.4
Name: romance
Version: 1.0
Summary: Coming Soon
Author: Saif
Author-email: saifullahanwar00040@gmail.com
Classifier: Programming Language :: Python :: 3
Classifier: License :: OSI Approved :: MIT License
Requires-Python: >=3.6
Dynamic: author
Dynamic: author-email
Dynamic: classifier
Dynamic: requires-python
Dynamic: summary
